libs/xelem-3.1.jar
pyany2json/__init__.py
pyany2json/document_factory.py
pyany2json/layex_table_parser.py
pyany2json/model.py
pyany2json/setup.py
pyany2json/types.py
pyany2json-0.1.3.dist-info/LICENSE
pyany2json-0.1.3.dist-info/METADATA
pyany2json-0.1.3.dist-info/WHEEL
pyany2json-0.1.3.dist-info/RECORD
