Metadata-Version: 2.1
Name: pyany2json
Version: 0.1.3
Summary: Python binding to Any2Json
Author: Romuald Rousseau
Author-email: romuald.rousseau@servier.com
Requires-Python: >=3.11,<4.0
Classifier: Programming Language :: Python :: 3
Classifier: Programming Language :: Python :: 3.11
Classifier: Programming Language :: Python :: 3.12
Requires-Dist: jpype1 (>=1.5.0,<2.0.0)
